LICENSE
MANIFEST.in
README.md
setup.cfg
setup.py
tap_db2/__init__.py
tap_db2/__main__.py
tap_db2/common.py
tap_db2/resolve.py
tap_db2/sync.py
tap_db2.egg-info/PKG-INFO
tap_db2.egg-info/SOURCES.txt
tap_db2.egg-info/dependency_links.txt
tap_db2.egg-info/entry_points.txt
tap_db2.egg-info/requires.txt
tap_db2.egg-info/top_level.txt
tap_db2/discovery/__init__.py
tap_db2/discovery/schemas.py